entityd/__init__.py
entityd/__main__.py
entityd/apacheme.py
entityd/connections.py
entityd/core.py
entityd/declentity.py
entityd/endpointme.py
entityd/entityupdate.py
entityd/fileme.py
entityd/health.py
entityd/hookspec.py
entityd/hostme.py
entityd/kvstore.py
entityd/mesend.py
entityd/monitor.py
entityd/mysqlme.py
entityd/pm.py
entityd/postgresme.py
entityd/processme.py
entityd/kubernetes/__init__.py
entityd/kubernetes/cluster.py
entityd/kubernetes/daemonset.py
entityd/kubernetes/deployment.py
entityd/kubernetes/kubernetes.py
entityd/kubernetes/node.py
entityd/kubernetes/replicaset.py
entityd/kubernetes/replicationcontroller.py
entityd/kubernetes/service.py
entityd-0.21.0.dist-info/DESCRIPTION.rst
entityd-0.21.0.dist-info/METADATA
entityd-0.21.0.dist-info/RECORD
entityd-0.21.0.dist-info/WHEEL
entityd-0.21.0.dist-info/entry_points.txt
entityd-0.21.0.dist-info/metadata.json
entityd-0.21.0.dist-info/top_level.txt
