Metadata-Version: 2.0
Name: entityd
Version: 0.21.0
Summary: Entity monitoring agent for cobe.io
Home-page: https://bitbucket.org/cobeio/act
Author: cobe.io
Author-email: info@cobe.io
License: LGPLv3
Keywords: topology performance availability monitoring
Platform: UNKNOWN
Classifier: Development Status :: 4 - Beta
Classifier: License :: OSI Approved :: GNU Lesser General Public License v3 (LGPLv3)
Classifier: Topic :: Software Development :: Libraries
Classifier: Programming Language :: Python :: 3 :: Only
Classifier: Programming Language :: Python :: 3.4
Classifier: Programming Language :: Python :: 3.5
Requires-Dist: Logbook
Requires-Dist: cobe-act
Requires-Dist: docker-py
Requires-Dist: kube (==0.10.0)
Requires-Dist: msgpack-python (>=0.4.5,<0.5)
Requires-Dist: python-cobe
Requires-Dist: pyyaml
Requires-Dist: pyzmq (>=14.7,<15.0)
Requires-Dist: requests (>=2.11.1)
Requires-Dist: setuptools
Requires-Dist: syskit
Requires-Dist: voluptuous (>=0.8.7,<0.9)
